.gitignore
.travis.yml
CHANGELOG.rst
COPYING
MANIFEST.in
README.rst
appveyor.yml
setup.cfg
setup.py
test-requirements.txt
tox.ini
docs/Makefile
docs/conf.py
docs/creating.rst
docs/errors.rst
docs/faq.rst
docs/index.rst
docs/jsonschema_role.py
docs/make.bat
docs/references.rst
docs/requirements.txt
docs/spelling-wordlist.txt
docs/validate.rst
json/.gitignore
json/.travis.yml
json/LICENSE
json/README.md
json/index.js
json/package.json
json/test-schema.json
json/tox.ini
json/bin/jsonschema_suite
json/remotes/integer.json
json/remotes/name.json
json/remotes/subSchemas.json
json/remotes/folder/folderInteger.json
json/tests/draft3/additionalItems.json
json/tests/draft3/additionalProperties.json
json/tests/draft3/default.json
json/tests/draft3/dependencies.json
json/tests/draft3/disallow.json
json/tests/draft3/divisibleBy.json
json/tests/draft3/enum.json
json/tests/draft3/extends.json
json/tests/draft3/items.json
json/tests/draft3/maxItems.json
json/tests/draft3/maxLength.json
json/tests/draft3/maximum.json
json/tests/draft3/minItems.json
json/tests/draft3/minLength.json
json/tests/draft3/minimum.json
json/tests/draft3/pattern.json
json/tests/draft3/patternProperties.json
json/tests/draft3/properties.json
json/tests/draft3/ref.json
json/tests/draft3/refRemote.json
json/tests/draft3/required.json
json/tests/draft3/type.json
json/tests/draft3/uniqueItems.json
json/tests/draft3/optional/bignum.json
json/tests/draft3/optional/format.json
json/tests/draft3/optional/jsregex.json
json/tests/draft3/optional/zeroTerminatedFloats.json
json/tests/draft4/additionalItems.json
json/tests/draft4/additionalProperties.json
json/tests/draft4/allOf.json
json/tests/draft4/anyOf.json
json/tests/draft4/default.json
json/tests/draft4/definitions.json
json/tests/draft4/dependencies.json
json/tests/draft4/enum.json
json/tests/draft4/items.json
json/tests/draft4/maxItems.json
json/tests/draft4/maxLength.json
json/tests/draft4/maxProperties.json
json/tests/draft4/maximum.json
jsonschema_extended.egg-info/PKG-INFO
jsonschema_extended.egg-info/SOURCES.txt
jsonschema_extended.egg-info/dependency_links.txt
jsonschema_extended.egg-info/entry_points.txt
jsonschema_extended.egg-info/requires.txt
jsonschema_extended.egg-info/top_level.txt
